<?xml version="1.0"?>
<map id="TechdemoMap" format="1.0">

	<metadata>
		<param name="Name" value="city_new.xml" />
		<param name="Version" value="1" />
		<param name="Comment" value="Upcoming 2007.3 techdemo map." />
		<param name="Author" value="Zero-Projekt and FIFE team" />
	</metadata>

	<!-- Load tiles -->
	<dataset type="XML" source="fo_remake/datasets/tiles/test_tiles.xml" />

	<!-- Load objects -->
	<dataset type="XML" source="fo_remake/datasets/objects/test_objects.xml" />

	<!-- Load agent datasets -->
	<dataset type="XML" source="fo_remake/datasets/agents/humans/gunner.xml" />

	<elevation id="TechdemoMapElevation">
		<!-- TILE LAYER -->
		<layer id="TechdemoMapTileLayer" grid_type="square" x_scale="1" y_scale="1">
			<instances>
				<i o="Tiles:Test:panel_001" x="0" y="0" /><i o="Tiles:Test:panel_001" /><i o="Tiles:Test:panel_001" /><i o="Tiles:Test:panel_001" /><i o="Tiles:Test:panel_001" /><i o="Tiles:Test:Block" /><i o="Tiles:Test:Block" /><i o="Tiles:Test:Block" /><i o="Tiles:Test:Block" /><i o="Tiles:Test:Block" />
				<i o="Tiles:Test:panel_003" x="0" y="1" /><i o="Tiles:Test:panel_001" /><i o="Tiles:Test:panel_001" /><i o="Tiles:Test:panel_001" /><i o="Tiles:Test:panel_001" /><i o="Tiles:Test:Block" /><i o="Tiles:Test:Block" /><i o="Tiles:Test:Block" /><i o="Tiles:Test:Block" /><i o="Tiles:Test:Block" />
				<i o="Tiles:Test:panel_001" x="0" y="2" /><i o="Tiles:Test:panel_001" /><i o="Tiles:Test:panel_001" /><i o="Tiles:Test:panel_001" /><i o="Tiles:Test:panel_001" /><i o="Tiles:Test:Block" /><i o="Tiles:Test:Block" /><i o="Tiles:Test:Block" /><i o="Tiles:Test:Block" /><i o="Tiles:Test:Block" />
				<i o="Tiles:Test:panel_001" x="0" y="3" /><i o="Tiles:Test:panel_002" /><i o="Tiles:Test:panel_001" /><i o="Tiles:Test:panel_003" /><i o="Tiles:Test:panel_001" /><i o="Tiles:Test:Block" /><i o="Tiles:Test:Block" /><i o="Tiles:Test:Block" /><i o="Tiles:Test:Block" /><i o="Tiles:Test:Block" />
				<i o="Tiles:Test:panel_001" x="0" y="4" /><i o="Tiles:Test:panel_001" /><i o="Tiles:Test:panel_001" /><i o="Tiles:Test:panel_001" /><i o="Tiles:Test:panel_001" /><i o="Tiles:Test:Block" /><i o="Tiles:Test:Block" /><i o="Tiles:Test:Block" /><i o="Tiles:Test:Block" /><i o="Tiles:Test:Block" />
				<i o="Tiles:Test:Block" x="0" y="5" /><i o="Tiles:Test:Block" /><i o="Tiles:Test:Block" /><i o="Tiles:Test:Block" /><i o="Tiles:Test:Block" /><i o="Tiles:Test:Block" /><i o="Tiles:Test:Block" /><i o="Tiles:Test:Block" /><i o="Tiles:Test:Block" /><i o="Tiles:Test:Block" />
				<i o="Tiles:Test:Block" x="0" y="6" /><i o="Tiles:Test:Block" /><i o="Tiles:Test:Block" /><i o="Tiles:Test:Block" /><i o="Tiles:Test:Block" /><i o="Tiles:Test:Block" /><i o="Tiles:Test:Block" /><i o="Tiles:Test:Block" /><i o="Tiles:Test:Block" /><i o="Tiles:Test:Block" />
				<i o="Tiles:Test:Block" x="0" y="7" /><i o="Tiles:Test:Block" /><i o="Tiles:Test:Block" /><i o="Tiles:Test:Block" /><i o="Tiles:Test:Block" /><i o="Tiles:Test:Block" /><i o="Tiles:Test:Block" /><i o="Tiles:Test:Block" /><i o="Tiles:Test:Block" /><i o="Tiles:Test:Block" />
				<i o="Tiles:Test:Block" x="0" y="8" /><i o="Tiles:Test:Block" /><i o="Tiles:Test:Block" /><i o="Tiles:Test:Block" /><i o="Tiles:Test:Block" /><i o="Tiles:Test:Block" /><i o="Tiles:Test:Block" /><i o="Tiles:Test:Block" /><i o="Tiles:Test:Block" /><i o="Tiles:Test:Block" />
				<i o="Tiles:Test:Block" x="0" y="9" /><i o="Tiles:Test:Block" /><i o="Tiles:Test:Block" /><i o="Tiles:Test:Block" /><i o="Tiles:Test:Block" /><i o="Tiles:Test:Block" /><i o="Tiles:Test:Block" /><i o="Tiles:Test:Block" /><i o="Tiles:Test:Block" /><i o="Tiles:Test:Block" />
			</instances>		
		</layer>

		<!-- OBJECT LAYER -->
		<layer id="TechdemoMapObjectLayer" grid_type="square" x_offset="-1.5" y_offset="-1.5" x_scale="0.25" y_scale="0.25" rotation="0">
			<instances>
				<i o="PC" x="0" y="0" id="agent">
					<metadata>
						<param name="name" value="MyHero"/>
						<param name="story">
							Here is some text representing the story behind our hero.
							...and still some more text.
						</param>
					</metadata>
				</i>
				<i o="Object:Invisible" x="0" y="0" />
				<i o="Object:Invisible" x="0" y="1" />
				<i o="Object:Invisible" x="0" y="2" />
				<i o="Object:Invisible" x="0" y="3" />
				<i o="Object:Invisible" x="0" y="4" />
				<i o="Object:Invisible" x="0" y="5" />
				<i o="Object:Invisible" x="0" y="6" />
				<i o="Object:Invisible" x="0" y="7" />
				<i o="Object:Invisible" x="0" y="8" />
				<i o="Object:Invisible" x="0" y="9" />
				<i o="Object:Invisible" x="0" y="10" />
				<i o="Object:Invisible" x="0" y="11" />
				<i o="Object:Invisible" x="0" y="12" />
				<i o="Object:Invisible" x="0" y="13" />
				<i o="Object:Invisible" x="0" y="14" />
				<i o="Object:Invisible" x="0" y="15" />
				<i o="Object:Invisible" x="0" y="16" />
				<i o="Object:Invisible" x="0" y="17" />
				<i o="Object:Invisible" x="0" y="18" />
				<i o="Object:Invisible" x="0" y="19" />
				<i o="Object:Invisible" x="0" y="20" />

				<i o="Object:Invisible" x="1" y="0" />
				<i o="Object:Invisible" x="1" y="1" />
				<i o="Object:Invisible" x="1" y="2" />
				<i o="Object:Invisible" x="1" y="3" />
				<i o="Object:Invisible" x="1" y="4" />
				<i o="Object:Invisible" x="1" y="5" />
				<i o="Object:Invisible" x="1" y="6" />
				<i o="Object:Invisible" x="1" y="7" />
				<i o="Object:Invisible" x="1" y="8" />
				<i o="Object:Invisible" x="1" y="9" />
				<i o="Object:Invisible" x="1" y="10" />
				<i o="Object:Invisible" x="1" y="11" />
				<i o="Object:Invisible" x="1" y="12" />
				<i o="Object:Invisible" x="1" y="13" />
				<i o="Object:Invisible" x="1" y="14" />
				<i o="Object:Invisible" x="1" y="15" />
				<i o="Object:Invisible" x="1" y="16" />
				<i o="Object:Invisible" x="1" y="17" />
				<i o="Object:Invisible" x="1" y="18" />
				<i o="Object:Invisible" x="1" y="19" />
				<i o="Object:Invisible" x="1" y="20" />

				<i o="Object:Invisible" x="2" y="0" />
				<i o="Object:Invisible" x="2" y="1" />
				<i o="Object:Invisible" x="2" y="2" />
				<i o="Object:Invisible" x="2" y="3" />
				<i o="Object:Invisible" x="2" y="4" />
				<i o="Object:Invisible" x="2" y="5" />
				<i o="Object:Invisible" x="2" y="6" />
				<i o="Object:Invisible" x="2" y="7" />
				<i o="Object:Invisible" x="2" y="8" />
				<i o="Object:Invisible" x="2" y="9" />
				<i o="Object:Invisible" x="2" y="10" />
				<i o="Object:Invisible" x="2" y="11" />
				<i o="Object:Invisible" x="2" y="12" />
				<i o="Object:Invisible" x="2" y="13" />
				<i o="Object:Invisible" x="2" y="14" />
				<i o="Object:Invisible" x="2" y="15" />
				<i o="Object:Invisible" x="2" y="16" />
				<i o="Object:Invisible" x="2" y="17" />
				<i o="Object:Invisible" x="2" y="18" />
				<i o="Object:Invisible" x="2" y="19" />
				<i o="Object:Invisible" x="2" y="20" />

				<i o="Object:Invisible" x="3" y="0" />
				<i o="Object:Invisible" x="3" y="1" />
				<i o="Object:Invisible" x="3" y="2" />
				<i o="Object:Invisible" x="3" y="3" />
				<i o="Object:Invisible" x="3" y="4" />
				<i o="Object:Invisible" x="3" y="5" />
				<i o="Object:Invisible" x="3" y="6" />
				<i o="Object:Invisible" x="3" y="7" />
				<i o="Object:Invisible" x="3" y="8" />
				<i o="Object:Invisible" x="3" y="9" />
				<i o="Object:Invisible" x="3" y="10" />
				<i o="Object:Invisible" x="3" y="11" />
				<i o="Object:Invisible" x="3" y="12" />
				<i o="Object:Invisible" x="3" y="13" />
				<i o="Object:Invisible" x="3" y="14" />
				<i o="Object:Invisible" x="3" y="15" />
				<i o="Object:Invisible" x="3" y="16" />
				<i o="Object:Invisible" x="3" y="17" />
				<i o="Object:Invisible" x="3" y="18" />
				<i o="Object:Invisible" x="3" y="19" />
				<i o="Object:Invisible" x="3" y="20" />
				
				<i o="Object:Invisible" x="4" y="0" />
				<i o="Object:Invisible" x="4" y="1" />
				<i o="Object:Invisible" x="4" y="2" />
				<i o="Object:Invisible" x="4" y="3" />
				<i o="Object:Invisible" x="4" y="4" />
				<i o="Object:Invisible" x="4" y="5" />
				<i o="Object:Invisible" x="4" y="6" />
				<i o="Object:Invisible" x="4" y="7" />
				<i o="Object:Invisible" x="4" y="8" />
				<i o="Object:Invisible" x="4" y="9" />
				<i o="Object:Invisible" x="4" y="10" />
				<i o="Object:Invisible" x="4" y="11" />
				<i o="Object:Invisible" x="4" y="12" />
				<i o="Object:Invisible" x="4" y="13" />
				<i o="Object:Invisible" x="4" y="14" />
				<i o="Object:Invisible" x="4" y="15" />
				<i o="Object:Invisible" x="4" y="16" />
				<i o="Object:Invisible" x="4" y="17" />
				<i o="Object:Invisible" x="4" y="18" />
				<i o="Object:Invisible" x="4" y="19" />
				<i o="Object:Invisible" x="4" y="20" />

				<i o="Object:Invisible" x="5" y="0" />
				<i o="Object:Invisible" x="5" y="1" />
				<i o="Object:Invisible" x="5" y="2" />
				<i o="Object:Invisible" x="5" y="3" />
				<i o="Object:Invisible" x="5" y="4" />
				<i o="Object:Invisible" x="5" y="5" />
				<i o="Object:Invisible" x="5" y="6" />
				<i o="Object:Invisible" x="5" y="7" />
				<i o="Object:Invisible" x="5" y="8" />
				<i o="Object:Invisible" x="5" y="9" />
				<i o="Object:Invisible" x="5" y="10" />
				<i o="Object:Invisible" x="5" y="11" />
				<i o="Object:Invisible" x="5" y="12" />
				<i o="Object:Invisible" x="5" y="13" />
				<i o="Object:Invisible" x="5" y="14" />
				<i o="Object:Invisible" x="5" y="15" />
				<i o="Object:Invisible" x="5" y="16" />
				<i o="Object:Invisible" x="5" y="17" />
				<i o="Object:Invisible" x="5" y="18" />
				<i o="Object:Invisible" x="5" y="19" />
				<i o="Object:Invisible" x="5" y="20" />

				<i o="Object:Invisible" x="6" y="0" />
				<i o="Object:Invisible" x="6" y="1" />
				<i o="Object:Invisible" x="6" y="2" />
				<i o="Object:Invisible" x="6" y="3" />
				<i o="Object:Invisible" x="6" y="4" />
				<i o="Object:Invisible" x="6" y="5" />
				<i o="Object:Invisible" x="6" y="6" />
				<i o="Object:Invisible" x="6" y="7" />
				<i o="Object:Invisible" x="6" y="8" />
				<i o="Object:Invisible" x="6" y="9" />
				<i o="Object:Invisible" x="6" y="10" />
				<i o="Object:Invisible" x="6" y="11" />
				<i o="Object:Invisible" x="6" y="12" />
				<i o="Object:Invisible" x="6" y="13" />
				<i o="Object:Invisible" x="6" y="14" />
				<i o="Object:Invisible" x="6" y="15" />
				<i o="Object:Invisible" x="6" y="16" />
				<i o="Object:Invisible" x="6" y="17" />
				<i o="Object:Invisible" x="6" y="18" />
				<i o="Object:Invisible" x="6" y="19" />
				<i o="Object:Invisible" x="6" y="20" />

				<i o="Object:Invisible" x="7" y="0" />
				<i o="Object:Invisible" x="7" y="1" />
				<i o="Object:Invisible" x="7" y="2" />
				<i o="Object:Invisible" x="7" y="3" />
				<i o="Object:Invisible" x="7" y="4" />
				<i o="Object:Invisible" x="7" y="5" />
				<i o="Object:Invisible" x="7" y="6" />
				<i o="Object:Invisible" x="7" y="7" />
				<i o="Object:Invisible" x="7" y="8" />
				<i o="Object:Invisible" x="7" y="9" />
				<i o="Object:Invisible" x="7" y="10" />
				<i o="Object:Invisible" x="7" y="11" />
				<i o="Object:Invisible" x="7" y="12" />
				<i o="Object:Invisible" x="7" y="13" />
				<i o="Object:Invisible" x="7" y="14" />
				<i o="Object:Invisible" x="7" y="15" />
				<i o="Object:Invisible" x="7" y="16" />
				<i o="Object:Invisible" x="7" y="17" />
				<i o="Object:Invisible" x="7" y="18" />
				<i o="Object:Invisible" x="7" y="19" />
				<i o="Object:Invisible" x="7" y="20" />
				
				<i o="Object:Invisible" x="8" y="0" />
				<i o="Object:Invisible" x="8" y="1" />
				<i o="Object:Invisible" x="8" y="2" />
				<i o="Object:Invisible" x="8" y="3" />
				<i o="Object:Invisible" x="8" y="4" />
				<i o="Object:Invisible" x="8" y="5" />
				<i o="Object:Invisible" x="8" y="6" />
				<i o="Object:Invisible" x="8" y="7" />
				<i o="Object:Invisible" x="8" y="8" />
				<i o="Object:Invisible" x="8" y="9" />
				<i o="Object:Invisible" x="8" y="10" />
				<i o="Object:Invisible" x="8" y="11" />
				<i o="Object:Invisible" x="8" y="12" />
				<i o="Object:Invisible" x="8" y="13" />
				<i o="Object:Invisible" x="8" y="14" />
				<i o="Object:Invisible" x="8" y="15" />
				<i o="Object:Invisible" x="8" y="16" />
				<i o="Object:Invisible" x="8" y="17" />
				<i o="Object:Invisible" x="8" y="18" />
				<i o="Object:Invisible" x="8" y="19" />
				<i o="Object:Invisible" x="8" y="20" />

				<i o="Object:Invisible" x="9" y="0" />
				<i o="Object:Invisible" x="9" y="1" />
				<i o="Object:Invisible" x="9" y="2" />
				<i o="Object:Invisible" x="9" y="3" />
				<i o="Object:Invisible" x="9" y="4" />
				<i o="Object:Invisible" x="9" y="5" />
				<i o="Object:Invisible" x="9" y="6" />
				<i o="Object:Invisible" x="9" y="7" />
				<i o="Object:Invisible" x="9" y="8" />
				<i o="Object:Invisible" x="9" y="9" />
				<i o="Object:Invisible" x="9" y="10" />
				<i o="Object:Invisible" x="9" y="11" />
				<i o="Object:Invisible" x="9" y="12" />
				<i o="Object:Invisible" x="9" y="13" />
				<i o="Object:Invisible" x="9" y="14" />
				<i o="Object:Invisible" x="9" y="15" />
				<i o="Object:Invisible" x="9" y="16" />
				<i o="Object:Invisible" x="9" y="17" />
				<i o="Object:Invisible" x="9" y="18" />
				<i o="Object:Invisible" x="9" y="19" />
				<i o="Object:Invisible" x="9" y="20" />

				<i o="Object:Invisible" x="10" y="0" />
				<i o="Object:Invisible" x="10" y="1" />
				<i o="Object:Invisible" x="10" y="2" />
				<i o="Object:Invisible" x="10" y="3" />
				<i o="Object:Invisible" x="10" y="4" />
				<i o="Object:Invisible" x="10" y="5" />
				<i o="Object:Invisible" x="10" y="6" />
				<i o="Object:Invisible" x="10" y="7" />
				<i o="Object:Invisible" x="10" y="8" />
				<i o="Object:Invisible" x="10" y="9" />
				<i o="Object:Invisible" x="10" y="10" />
				<i o="Object:Invisible" x="10" y="11" />
				<i o="Object:Invisible" x="10" y="12" />
				<i o="Object:Invisible" x="10" y="13" />
				<i o="Object:Invisible" x="10" y="14" />
				<i o="Object:Invisible" x="10" y="15" />
				<i o="Object:Invisible" x="10" y="16" />
				<i o="Object:Invisible" x="10" y="17" />
				<i o="Object:Invisible" x="10" y="18" />
				<i o="Object:Invisible" x="10" y="19" />
				<i o="Object:Invisible" x="10" y="20" />

				<i o="Object:Invisible" x="11" y="0" />
				<i o="Object:Invisible" x="11" y="1" />
				<i o="Object:Invisible" x="11" y="2" />
				<i o="Object:Invisible" x="11" y="3" />
				<i o="Object:Invisible" x="11" y="4" />
				<i o="Object:Invisible" x="11" y="5" />
				<i o="Object:Invisible" x="11" y="6" />
				<i o="Object:Invisible" x="11" y="7" />
				<i o="Object:Invisible" x="11" y="8" />
				<i o="Object:Invisible" x="11" y="9" />
				<i o="Object:Invisible" x="11" y="10" />
				<i o="Object:Invisible" x="11" y="11" />
				<i o="Object:Invisible" x="11" y="12" />
				<i o="Object:Invisible" x="11" y="13" />
				<i o="Object:Invisible" x="11" y="14" />
				<i o="Object:Invisible" x="11" y="15" />
				<i o="Object:Invisible" x="11" y="16" />
				<i o="Object:Invisible" x="11" y="17" />
				<i o="Object:Invisible" x="11" y="18" />
				<i o="Object:Invisible" x="11" y="19" />
				<i o="Object:Invisible" x="11" y="20" />

				<i o="Object:Invisible" x="12" y="0" />
				<i o="Object:Invisible" x="12" y="1" />
				<i o="Object:Invisible" x="12" y="2" />
				<i o="Object:Invisible" x="12" y="3" />
				<i o="Object:Invisible" x="12" y="4" />
				<i o="Object:Invisible" x="12" y="5" />
				<i o="Object:Invisible" x="12" y="6" />
				<i o="Object:Invisible" x="12" y="7" />
				<i o="Object:Invisible" x="12" y="8" />
				<i o="Object:Invisible" x="12" y="9" />
				<i o="Object:Invisible" x="12" y="10" />
				<i o="Object:Invisible" x="12" y="11" />
				<i o="Object:Invisible" x="12" y="12" />
				<i o="Object:Invisible" x="12" y="13" />
				<i o="Object:Invisible" x="12" y="14" />
				<i o="Object:Invisible" x="12" y="15" />
				<i o="Object:Invisible" x="12" y="16" />
				<i o="Object:Invisible" x="12" y="17" />
				<i o="Object:Invisible" x="12" y="18" />
				<i o="Object:Invisible" x="12" y="19" />
				<i o="Object:Invisible" x="12" y="20" />

				<i o="Object:Invisible" x="13" y="0" />
				<i o="Object:Invisible" x="13" y="1" />
				<i o="Object:Invisible" x="13" y="2" />
				<i o="Object:Invisible" x="13" y="3" />
				<i o="Object:Invisible" x="13" y="4" />
				<i o="Object:Invisible" x="13" y="5" />
				<i o="Object:Invisible" x="13" y="6" />
				<i o="Object:Invisible" x="13" y="7" />
				<i o="Object:Invisible" x="13" y="8" />
				<i o="Object:Invisible" x="13" y="9" />
				<i o="Object:Invisible" x="13" y="10" />
				<i o="Object:Invisible" x="13" y="11" />
				<i o="Object:Invisible" x="13" y="12" />
				<i o="Object:Invisible" x="13" y="13" />
				<i o="Object:Invisible" x="13" y="14" />
				<i o="Object:Invisible" x="13" y="15" />
				<i o="Object:Invisible" x="13" y="16" />
				<i o="Object:Invisible" x="13" y="17" />
				<i o="Object:Invisible" x="13" y="18" />
				<i o="Object:Invisible" x="13" y="19" />
				<i o="Object:Invisible" x="13" y="20" />
				
				<i o="Object:Invisible" x="14" y="0" />
				<i o="Object:Invisible" x="14" y="1" />
				<i o="Object:Invisible" x="14" y="2" />
				<i o="Object:Invisible" x="14" y="3" />
				<i o="Object:Invisible" x="14" y="4" />
				<i o="Object:Invisible" x="14" y="5" />
				<i o="Object:Invisible" x="14" y="6" />
				<i o="Object:Invisible" x="14" y="7" />
				<i o="Object:Invisible" x="14" y="8" />
				<i o="Object:Invisible" x="14" y="9" />
				<i o="Object:Invisible" x="14" y="10" />
				<i o="Object:Invisible" x="14" y="11" />
				<i o="Object:Invisible" x="14" y="12" />
				<i o="Object:Invisible" x="14" y="13" />
				<i o="Object:Invisible" x="14" y="14" />
				<i o="Object:Invisible" x="14" y="15" />
				<i o="Object:Invisible" x="14" y="16" />
				<i o="Object:Invisible" x="14" y="17" />
				<i o="Object:Invisible" x="14" y="18" />
				<i o="Object:Invisible" x="14" y="19" />
				<i o="Object:Invisible" x="14" y="20" />

				<i o="Object:Invisible" x="15" y="0" />
				<i o="Object:Invisible" x="15" y="1" />
				<i o="Object:Invisible" x="15" y="2" />
				<i o="Object:Invisible" x="15" y="3" />
				<i o="Object:Invisible" x="15" y="4" />
				<i o="Object:Invisible" x="15" y="5" />
				<i o="Object:Invisible" x="15" y="6" />
				<i o="Object:Invisible" x="15" y="7" />
				<i o="Object:Invisible" x="15" y="8" />
				<i o="Object:Invisible" x="15" y="9" />
				<i o="Object:Invisible" x="15" y="10" />
				<i o="Object:Invisible" x="15" y="11" />
				<i o="Object:Invisible" x="15" y="12" />
				<i o="Object:Invisible" x="15" y="13" />
				<i o="Object:Invisible" x="15" y="14" />
				<i o="Object:Invisible" x="15" y="15" />
				<i o="Object:Invisible" x="15" y="16" />
				<i o="Object:Invisible" x="15" y="17" />
				<i o="Object:Invisible" x="15" y="18" />
				<i o="Object:Invisible" x="15" y="19" />
				<i o="Object:Invisible" x="15" y="20" />

				<i o="Object:Invisible" x="16" y="0" />
				<i o="Object:Invisible" x="16" y="1" />
				<i o="Object:Invisible" x="16" y="2" />
				<i o="Object:Invisible" x="16" y="3" />
				<i o="Object:Invisible" x="16" y="4" />
				<i o="Object:Invisible" x="16" y="5" />
				<i o="Object:Invisible" x="16" y="6" />
				<i o="Object:Invisible" x="16" y="7" />
				<i o="Object:Invisible" x="16" y="8" />
				<i o="Object:Invisible" x="16" y="9" />
				<i o="Object:Invisible" x="16" y="10" />
				<i o="Object:Invisible" x="16" y="11" />
				<i o="Object:Invisible" x="16" y="12" />
				<i o="Object:Invisible" x="16" y="13" />
				<i o="Object:Invisible" x="16" y="14" />
				<i o="Object:Invisible" x="16" y="15" />
				<i o="Object:Invisible" x="16" y="16" />
				<i o="Object:Invisible" x="16" y="17" />
				<i o="Object:Invisible" x="16" y="18" />
				<i o="Object:Invisible" x="16" y="19" />
				<i o="Object:Invisible" x="16" y="20" />

				<i o="Object:Invisible" x="17" y="0" />
				<i o="Object:Invisible" x="17" y="1" />
				<i o="Object:Invisible" x="17" y="2" />
				<i o="Object:Invisible" x="17" y="3" />
				<i o="Object:Invisible" x="17" y="4" />
				<i o="Object:Invisible" x="17" y="5" />
				<i o="Object:Invisible" x="17" y="6" />
				<i o="Object:Invisible" x="17" y="7" />
				<i o="Object:Invisible" x="17" y="8" />
				<i o="Object:Invisible" x="17" y="9" />
				<i o="Object:Invisible" x="17" y="10" />
				<i o="Object:Invisible" x="17" y="11" />
				<i o="Object:Invisible" x="17" y="12" />
				<i o="Object:Invisible" x="17" y="13" />
				<i o="Object:Invisible" x="17" y="14" />
				<i o="Object:Invisible" x="17" y="15" />
				<i o="Object:Invisible" x="17" y="16" />
				<i o="Object:Invisible" x="17" y="17" />
				<i o="Object:Invisible" x="17" y="18" />
				<i o="Object:Invisible" x="17" y="19" />
				<i o="Object:Invisible" x="17" y="20" />
				
				<i o="Object:Invisible" x="18" y="0" />
				<i o="Object:Invisible" x="18" y="1" />
				<i o="Object:Invisible" x="18" y="2" />
				<i o="Object:Invisible" x="18" y="3" />
				<i o="Object:Invisible" x="18" y="4" />
				<i o="Object:Invisible" x="18" y="5" />
				<i o="Object:Invisible" x="18" y="6" />
				<i o="Object:Invisible" x="18" y="7" />
				<i o="Object:Invisible" x="18" y="8" />
				<i o="Object:Invisible" x="18" y="9" />
				<i o="Object:Invisible" x="18" y="10" />
				<i o="Object:Invisible" x="18" y="11" />
				<i o="Object:Invisible" x="18" y="12" />
				<i o="Object:Invisible" x="18" y="13" />
				<i o="Object:Invisible" x="18" y="14" />
				<i o="Object:Invisible" x="18" y="15" />
				<i o="Object:Invisible" x="18" y="16" />
				<i o="Object:Invisible" x="18" y="17" />
				<i o="Object:Invisible" x="18" y="18" />
				<i o="Object:Invisible" x="18" y="19" />
				<i o="Object:Invisible" x="18" y="20" />

				<i o="Object:Invisible" x="19" y="0" />
				<i o="Object:Invisible" x="19" y="1" />
				<i o="Object:Invisible" x="19" y="2" />
				<i o="Object:Invisible" x="19" y="3" />
				<i o="Object:Invisible" x="19" y="4" />
				<i o="Object:Invisible" x="19" y="5" />
				<i o="Object:Invisible" x="19" y="6" />
				<i o="Object:Invisible" x="19" y="7" />
				<i o="Object:Invisible" x="19" y="8" />
				<i o="Object:Invisible" x="19" y="9" />
				<i o="Object:Invisible" x="19" y="10" />
				<i o="Object:Invisible" x="19" y="11" />
				<i o="Object:Invisible" x="19" y="12" />
				<i o="Object:Invisible" x="19" y="13" />
				<i o="Object:Invisible" x="19" y="14" />
				<i o="Object:Invisible" x="19" y="15" />
				<i o="Object:Invisible" x="19" y="16" />
				<i o="Object:Invisible" x="19" y="17" />
				<i o="Object:Invisible" x="19" y="18" />
				<i o="Object:Invisible" x="19" y="19" />
				<i o="Object:Invisible" x="19" y="20" />

				<i o="Object:Invisible" x="20" y="0" />
				<i o="Object:Invisible" x="20" y="1" />
				<i o="Object:Invisible" x="20" y="2" />
				<i o="Object:Invisible" x="20" y="3" />
				<i o="Object:Invisible" x="20" y="4" />
				<i o="Object:Invisible" x="20" y="5" />
				<i o="Object:Invisible" x="20" y="6" />
				<i o="Object:Invisible" x="20" y="7" />
				<i o="Object:Invisible" x="20" y="8" />
				<i o="Object:Invisible" x="20" y="9" />
				<i o="Object:Invisible" x="20" y="10" />
				<i o="Object:Invisible" x="20" y="11" />
				<i o="Object:Invisible" x="20" y="12" />
				<i o="Object:Invisible" x="20" y="13" />
				<i o="Object:Invisible" x="20" y="14" />
				<i o="Object:Invisible" x="20" y="15" />
				<i o="Object:Invisible" x="20" y="16" />
				<i o="Object:Invisible" x="20" y="17" />
				<i o="Object:Invisible" x="20" y="18" />
				<i o="Object:Invisible" x="20" y="19" />
				<i o="Object:Invisible" x="20" y="20" />
			</instances>
		</layer>
	</elevation>
</map>
