<ResizableWindow title="FlowContainer Example" min_size="180, 140" size="520,400">
  <Label text="Horizontal FlowContainer"/>
  <HBox hexpand="1" vexpand="1">
    <FlowContainer layout="horizontal" hexpand="1" border_size="2" alignment="4">
      <Label text="The "/>
      <Label text="FlowContainer" foreground_color="255,0,0" font="samanata_large_recoloring"/>
      <Label text="can "/>
      <Label text="hold "/>
      <Label text="different "/>
      <Label text="types "/>
      <Label text="of "/>
      <Label text="Widgets "/>
      <Label text="and "/>
      <Label text="can "/>
      <Label text="sort "/>
      <Label text="them "/>
      <Label text="horizontal" foreground_color="255,255,0" font="samanata_large_recoloring"/>
      <Label text="or "/>
      <Label text="vertical. " foreground_color="0,0,255" font="samanata_large_recoloring"/>
      <AnimationIcon animation="gui/animations/cog/animation.xml"/>
      <Label text="It's "/>
      <Label text="also "/>
      <Label text="possible "/>
      <Label text="to "/>
      <Label text="change "/>
      <Label text="the "/>
      <Label text="alignment."/>
    </FlowContainer>
  </HBox>
  
  <Label text="Vertical FlowContainer"/>
  <VBox hexpand="1" vexpand="1">
    <FlowContainer layout="vertical" vexpand="1" border_size="2" alignment="4">
      <Label text="The "/>
      <Label text="FlowContainer" foreground_color="255,0,0" font="samanata_large_recoloring"/>
      <Label text="can "/>
      <Label text="hold "/>
      <Label text="different "/>
      <Label text="types "/>
      <Label text="of "/>
      <Label text="Widgets "/>
      <Label text="and "/>
      <Label text="can "/>
      <Label text="sort "/>
      <Label text="them "/>
      <Label text="horizontal" foreground_color="255,255,0" font="samanata_large_recoloring"/>
      <Label text="or "/>
      <Label text="vertical. " foreground_color="0,0,255" font="samanata_large_recoloring"/>
      <AnimationIcon animation="gui/animations/cog/animation.xml"/>
      <Label text="It's "/>
      <Label text="also "/>
      <Label text="possible "/>
      <Label text="to "/>
      <Label text="change "/>
      <Label text="the "/>
      <Label text="alignment."/>
    </FlowContainer>
  </VBox>
  
  <Button name="closeButton" text="Close"/>
</ResizableWindow>
