<Panel title="Cell view" position="10,700" min_size="200,100">
	<HBox>
		<Spacer min_size="150"/>
		<ImageButton up_image="gui/icons/help.png" down_image="gui/icons/help.png" hover_image="gui/icons/help.png" name="show_help" text="      Help " />
	</HBox>

	<Label name="current_mode" text="Current mode:"/>
  <HBox name="expert_mode_wrapper">
    <CheckBox name="expert_mode" text="Expert mode" min_size="120,20" />
  </HBox>

	<Label text="           Selected cell" background_color="0,0,0" />
	<HBox>
		<Label text="Coordinates: " min_size="85,20"/>
´		<Label name="cell_coords" text="" min_size="40,20"/>
	</HBox>
	
	<Label name="cell_blocking_policy_section" text="                 cell blocking policy:" background_color="0,0,0" />	
	<VBox name="cell_blocking_policy_wrapper">		
		<HBox>
			<Label text="Blocking policy: " min_size="85,20"/>
			<ToggleButton group="blocking_policy_switch" name="blocking_policy_no_blocking" text="No blocking" toggled="1" />
			<ToggleButton group="blocking_policy_switch" name="blocking_policy_blocking" text="Blocking" />
		</HBox>
	</VBox>
	
	<Label name="cell_costs_section" text="                 cell costs:" background_color="0,0,0" />	
	<VBox name="cell_costs_wrapper">
		<HBox>
			<Label text="Defaul cost multiplier: " min_size="85,20"/>
	´		<TextBox name="default_cost_multiplier" text="-" min_size="40,20"/>	
			<Button name="apply_cost_multiplier" text="Apply" min_size="40,20" />		
		</HBox>	
		<Label text="Custom cost data: (evaluation on client side)"/>	
		<HBox name="cost_mini_editor">
			<TextBox name="mini_editor_cost_id" text="id"/>
			<TextBox name="mini_editor_cost_value" text="value" />
			<Button name="mini_editor_cost_save" text="Save" />
		</HBox>
		<HBox>
			<ScrollArea min_size="150,50" horizontal_scrollbar="0">
				<ListBox 
					name="cost_entries"
				/>
			</ScrollArea>					
			<VBox>
				<Button name="add_cost_entry" text="New" min_size="40,20" />
				<Button name="edit_current_cost_entry" text="Edit" min_size="40,20" />			
				<Button name="remove_current_cost_entry" text="Remove" min_size="40,20" />
			</VBox>
		</HBox>
	</VBox>	
	
	<Label name="cell_speed_section" text="                 cell speed factor:" background_color="0,0,0" />	
	<VBox name="cell_speed_wrapper">
		<HBox>
			<Label text="Multiplier: " min_size="85,20"/>
	´		<TextBox name="speed_multiplier" text="-" min_size="40,20"/>	
			<Button name="apply_speed_multiplier" text="Apply" min_size="40,20" />
		</HBox>	
	</VBox>


	<Label name="transition_wizard_section" text="           Transition creation ('Pathfinder portals')" background_color="0,0,0" />
	<VBox name="transition_wizard_wrapper">
		<HBox name="transition_wizard">
			<ToggleButton name="transition_start" text="P" base_color="0,113,0,255" min_size="20,20" max_size="20,20" size="20,20" />
			<ToggleButton name="transition_end" text="P" base_color="228,72,70,255" min_size="20,20" max_size="20,20" size="20,20" />
			<Button name="transition_create" text="Create" min_size="20,20" />
			<CheckBox name="transition_immediate" text="immediate" min_size="120,20" />
		</HBox>		
	</VBox>		
	
	<Label name="instance_on_cell_section" text="           Instance(s) on cell" background_color="0,0,0" />
	<VBox name="instance_on_cell_wrapper">
		<ScrollArea min_size="200,80">
			<VBox name="cell_instance_wrapper">		
			</VBox>
		</ScrollArea>
	</VBox>
			
</Panel>
